[
  {
    "_id": "question_k8rjffv9w",
    "status": "Pending",
    "answer": "",
    "tags": [
      "offer-letter",
      "delay"
    ],
    "matchedFAQIds": [],
    "name": "Aarav Sharma",
    "email": "aarav.sharma@example.com",
    "category": "Offer Letter",
    "title": "Offer letter not received yet",
    "description": "I was selected on May 20th but have not received my offer letter in my inbox. Please help me get the letter.",
    "createdAt": "2026-05-31T05:44:11.152Z",
    "updatedAt": "2026-05-31T07:44:11.152Z"
  },
  {
    "_id": "question_qm7joqgyr",
    "status": "Pending",
    "answer": "",
    "tags": [
      "certificate",
      "noc",
      "verification"
    ],
    "matchedFAQIds": [],
    "name": "Sneha Patel",
    "email": "sneha.patel@example.com",
    "category": "Certificate",
    "title": "NOC verification taking too long",
    "description": "I uploaded my No Objection Certificate 4 days ago, but the status is still showing as pending verification. When will it be verified?",
    "createdAt": "2026-05-31T02:44:11.152Z",
    "updatedAt": "2026-05-31T07:44:11.152Z"
  },
  {
    "_id": "question_2a5r4eipb",
    "status": "Pending",
    "answer": "",
    "tags": [
      "certificate",
      "noc",
      "approval"
    ],
    "matchedFAQIds": [],
    "name": "Sneha Patel",
    "email": "sneha.patel@example.com",
    "category": "Certificate",
    "title": "NOC approval is delayed",
    "description": "Uploaded my NOC letter 5 days ago, but it has not been reviewed by any coordinator yet. Please speed it up.",
    "createdAt": "2026-05-31T03:44:11.152Z",
    "updatedAt": "2026-05-31T07:44:11.152Z"
  },
  {
    "_id": "question_q0zs8vqff",
    "status": "Pending",
    "answer": "",
    "tags": [
      "portal-login",
      "password-reset"
    ],
    "matchedFAQIds": [],
    "name": "Rahul Verma",
    "email": "rahul.verma@example.com",
    "category": "Login Issues",
    "title": "Forgot password reset not working",
    "description": "I clicked forgot password but did not receive any reset link in my Gmail inbox. Checked spam as well.",
    "createdAt": "2026-05-30T21:44:11.152Z",
    "updatedAt": "2026-05-31T07:44:11.152Z"
  },
  {
    "_id": "question_ax24xa8qo",
    "status": "Pending",
    "answer": "",
    "tags": [
      "selection",
      "confirmation",
      "error"
    ],
    "matchedFAQIds": [],
    "name": "Priya Iyer",
    "email": "priya.iyer@example.com",
    "category": "Selection Confirmation",
    "title": "Confirming selection link shows error",
    "description": "When I click the confirm selection button in my selection email, the page says \"Link Expired\". How do I confirm my selection now?",
    "createdAt": "2026-05-30T07:44:11.152Z",
    "updatedAt": "2026-05-31T07:44:11.152Z"
  },
  {
    "_id": "question_q80rvtxn4",
    "status": "Pending",
    "answer": "",
    "tags": [
      "login-issues",
      "portal-login"
    ],
    "matchedFAQIds": [],
    "name": "Thanishka",
    "email": "obilisettithanishka@gmail.com",
    "category": "Login Issues",
    "title": "I cannot login into Samagama.in",
    "description": "Login issue",
    "screenshotUrl": "",
    "createdAt": "2026-05-31T07:50:56.729Z",
    "updatedAt": "2026-05-31T07:50:56.729Z"
  }
]